{
    "Nigeria": {
      "Abia": ["Aba North", "Aba South", "Arochukwu", "Bende", "Ikwuano"],
      "Adamawa": ["Demsa", "Fufore", "Ganye", "Girei", "Hong"],
      "Akwa Ibom": ["Abak", "Eastern Obolo", "Eket", "Essien Udim", "Etim Ekpo"],
      "Anambra": ["Aguata", "Awka North", "Awka South", "Ayamelum", "Dunukofia"],
      "Bauchi": ["Bauchi", "Bogoro", "Damban", "Darazo", "Dass"],
      "Bayelsa": ["Brass", "Ekeremor", "Kolokuma/Opokuma", "Nembe", "Ogbia"],
      "Benue": ["Ado", "Agatu", "Apa", "Buruku", "Gboko"],
      "Borno": ["Abadam", "Askira/Uba", "Bama", "Bayo", "Biu"],
      "Cross River": ["Abi", "Akamkpa", "Akpabuyo", "Bakassi", "Bekwara"],
      "Delta": ["Aniocha North", "Aniocha South", "Bomadi", "Burutu", "Ethiope East"],
      "Ebonyi": ["Abakaliki", "Afikpo North", "Afikpo South", "Ebonyi", "Ezza North"],
      "Edo": ["Akoko Edo", "Egor", "Esan Central", "Esan North-East", "Esan South-East"],
      "Ekiti": ["Ado Ekiti", "Efon", "Ekiti East", "Ekiti Southwest", "Emure"],
      "Enugu": ["Aninri", "Awgu", "Enugu East", "Enugu North", "Enugu South"],
      "Gombe": ["Akko", "Balanga", "Billiri", "Dukku", "Funakaye"],
      "Imo": ["Aboh Mbaise", "Ahiazu Mbaise", "Ehime Mbano", "Ezinihitte", "Ideato North"],
      "Jigawa": ["Auyo", "Babura", "Birnin Kudu", "Birniwa", "Buji"],
      "Kaduna": ["Birnin Gwari", "Chikun", "Giwa", "Igabi", "Ikara"],
      "Kano": ["Ajingi", "Albasu", "Bagwai", "Bebeji", "Bichi"],
      "Katsina": ["Bakori", "Batagarawa", "Batsari", "Baure", "Bindawa"],
      "Kebbi": ["Aleiro", "Arewa Dandi", "Argungu", "Augie", "Bagudo"],
      "Kogi": ["Adavi", "Ajaokuta", "Ankpa", "Bassa", "Dekina"],
      "Kwara": ["Asa", "Baruten", "Edu", "Ekiti", "Ilorin East"],
      "Lagos": ["Agege", "Ajeromi-Ifelodun", "Alimosho", "Amuwo-Odofin", "Apapa"],
      "Nasarawa": ["Akwanga", "Awe", "Doma", "Karu", "Keana"],
      "Niger": ["Agaie", "Agwara", "Bida", "Borgu", "Bosso"],
      "Ogun": ["Abeokuta North", "Abeokuta South", "Ado-Odo/Ota", "Egbado North", "Egbado South"],
      "Ondo": ["Akoko North-East", "Akoko North-West", "Akure North", "Akure South", "Ese Odo"],
      "Osun": ["Aiyedaade", "Aiyedire", "Atakunmosa East", "Atakunmosa West", "Ayedaade"],
      "Oyo": ["Afijio", "Akinyele", "Atiba", "Atisbo", "Egbeda"],
      "Plateau": ["Barkin Ladi", "Bassa", "Bokkos", "Jos East", "Jos North"],
      "Rivers": ["Abua/Odual", "Ahoada East", "Ahoada West", "Akuku-Toru"]
    }
}